amounts/main.py
amounts/utils/array.py
amounts/utils/config.py
amounts/utils/digit.py
amounts/utils/file.py
amounts/utils/fuzz.py
amounts/utils/general.py
amounts/utils/validate.py
wordlists/all.txt
wordlists/hundred.txt
wordlists/hundred_thousand.txt
wordlists/milion.txt
wordlists/one.txt
wordlists/other.txt
wordlists/ten.txt
wordlists/ten_thousand.txt
wordlists/thousand.txt
wordlists/zero.txt
wordlists/zero_point_one.txt
amounts-4.2.dist-info/LICENSE
amounts-4.2.dist-info/METADATA
amounts-4.2.dist-info/WHEEL
amounts-4.2.dist-info/entry_points.txt
amounts-4.2.dist-info/top_level.txt
amounts-4.2.dist-info/RECORD
