Metadata-Version: 2.1
Name: amounts
Version: 4.2
Summary: Generate a wordlist to fuzz amounts or any other numerical values.
Author: Ivan Sincek
Project-URL: Homepage, https://github.com/ivan-sincek/amounts
Classifier: Programming Language :: Python :: 3
Classifier: License :: OSI Approved :: MIT License
Classifier: Operating System :: OS Independent
Requires-Python: >=3.10
License-File: LICENSE
